gds_fdtd/__init__.py
gds_fdtd/core.py
gds_fdtd/logging_config.py
gds_fdtd/lyprocessor.py
gds_fdtd/simprocessor.py
gds_fdtd/solver.py
gds_fdtd/solver_lumerical.py
gds_fdtd/solver_tidy3d.py
gds_fdtd/sparams.py
gds_fdtd-0.4.0.dist-info/licenses/LICENSE
gds_fdtd-0.4.0.dist-info/WHEEL
gds_fdtd-0.4.0.dist-info/METADATA
gds_fdtd-0.4.0.dist-info/RECORD
