Metadata-Version: 2.4
Name: gds_fdtd
Version: 0.4.0
Summary: Minimalist utilities for photonic FDTD workflows.
Keywords: python,photonics,fdtd,simulation,optics,eda,electromagnetics,gds,silicon-photonics
Author-email: Mustafa Hammood <mustafa@siepic.com>
Requires-Python: >=3.10,<3.14
Classifier: Programming Language :: Python :: 3
Classifier: Programming Language :: Python :: 3 :: Only
Classifier: Programming Language :: Python :: 3.11
Classifier: Operating System :: OS Independent
Classifier: License :: OSI Approved :: MIT License
License-File: LICENSE
Requires-Dist: numpy>=1.25
Requires-Dist: klayout>=0.30.1
Requires-Dist: matplotlib>=3.8
Requires-Dist: shapely>=2.0
Requires-Dist: PyYAML>=6.0
Requires-Dist: pip>=23.3 ; extra == "dev"
Requires-Dist: wheel>=0.42.0 ; extra == "dev"
Requires-Dist: twine>=4.0.2 ; extra == "dev"
Requires-Dist: bump2version>=1.0.1 ; extra == "dev"
Requires-Dist: watchdog>=3.0.0 ; extra == "dev"
Requires-Dist: pytest>=8.1 ; extra == "dev"
Requires-Dist: pytest-cov>=5.0 ; extra == "dev"
Requires-Dist: coverage ; extra == "dev"
Requires-Dist: ruff>=0.4.3 ; extra == "dev"
Requires-Dist: sphinx>=7.0 ; extra == "dev"
Requires-Dist: sphinx-rtd-theme>=1.2.0 ; extra == "dev"
Requires-Dist: docutils<0.23 ; extra == "dev"
Requires-Dist: sphinx-toggleprompt>=0.1.0 ; extra == "dev"
Requires-Dist: sphinx-copybutton>=0.5.2 ; extra == "dev"
Requires-Dist: sphinx-design>=0.5.0 ; extra == "dev"
Requires-Dist: furo>=2024.08.06 ; extra == "dev"
Requires-Dist: gdsfactory>=9.5.7,<10 ; extra == "gdsfactory"
Requires-Dist: prefab>=1.2.0 ; extra == "prefab"
Requires-Dist: SiEPIC>=0.5.25 ; extra == "siepic"
Requires-Dist: tidy3d>=2.8.3,<2.9 ; extra == "tidy3d"
Project-URL: Bug Tracker, https://github.com/SiEPIC/gds_fdtd/issues
Project-URL: Homepage, https://github.com/SiEPIC/gds_fdtd
Project-URL: Repository, https://github.com/SiEPIC/gds_fdtd
Provides-Extra: dev
Provides-Extra: gdsfactory
Provides-Extra: prefab
Provides-Extra: siepic
Provides-Extra: tidy3d
